run_dynamodblocal/__init__.py
run_dynamodblocal/version.py
run_dynamodblocal-0.2.0.dist-info/LICENSE
run_dynamodblocal-0.2.0.dist-info/METADATA
run_dynamodblocal-0.2.0.dist-info/WHEEL
run_dynamodblocal-0.2.0.dist-info/top_level.txt
run_dynamodblocal-0.2.0.dist-info/RECORD
