Metadata-Version: 2.1
Name: run-dynamodblocal
Version: 0.2.0
Summary: Run an in-memory DynamoDBLocal for testing
Home-page: https://github.com/rtweeks/run-dynamodblocal
Author: Richard T. Weeks
Author-email: rtweeks21@gmail.com
License: Apache License 2.0
Platform: UNKNOWN
Classifier: Programming Language :: Python :: 3
Classifier: License :: OSI Approved :: MIT License
Classifier: Operating System :: OS Independent
Requires-Python: >=3.6
License-File: LICENSE
Requires-Dist: psutil (~=5.8) ; sys_platform == "win32"
Provides-Extra: boto3
Requires-Dist: boto3-mocking (<2) ; extra == 'boto3'
